encoded_core/__init__.py
encoded_core/file_views.py
encoded_core/local_roles.py
encoded_core/page_views.py
encoded_core/project_defs.py
encoded_core/qc_views.py
encoded_core/schemas/document.json
encoded_core/schemas/file.json
encoded_core/schemas/file_format.json
encoded_core/schemas/file_processed.json
encoded_core/schemas/file_reference.json
encoded_core/schemas/file_submitted.json
encoded_core/schemas/higlass_view_config.json
encoded_core/schemas/image.json
encoded_core/schemas/meta_workflow.json
encoded_core/schemas/meta_workflow_run.json
encoded_core/schemas/mixins.json
encoded_core/schemas/page.json
encoded_core/schemas/quality_metric.json
encoded_core/schemas/quality_metric_generic.json
encoded_core/schemas/software.json
encoded_core/schemas/static_section.json
encoded_core/schemas/tracking_item.json
encoded_core/schemas/user_content.json
encoded_core/schemas/workflow.json
encoded_core/schemas/workflow_run.json
encoded_core/schemas/workflow_run_awsem.json
encoded_core/tests/__init__.py
encoded_core/tests/conftest.py
encoded_core/tests/conftest_settings.py
encoded_core/tests/datafixtures.py
encoded_core/tests/test_download_cli.py
encoded_core/tests/test_types_file.py
encoded_core/tests/test_types_file_format.py
encoded_core/tests/test_types_meta_workflow.py
encoded_core/tests/test_types_software.py
encoded_core/tests/test_types_workflow.py
encoded_core/types/__init__.py
encoded_core/types/document.py
encoded_core/types/file.py
encoded_core/types/file_format.py
encoded_core/types/file_processed.py
encoded_core/types/file_reference.py
encoded_core/types/file_submitted.py
encoded_core/types/higlass_view_config.py
encoded_core/types/image.py
encoded_core/types/meta_workflow.py
encoded_core/types/page.py
encoded_core/types/quality_metric.py
encoded_core/types/quality_metric_generic.py
encoded_core/types/software.py
encoded_core/types/tracking_item.py
encoded_core/types/user_content.py
encoded_core/types/workflow.py
encoded_core/upgrade.py
encoded_core-0.9.6.dist-info/LICENSE
encoded_core-0.9.6.dist-info/METADATA
encoded_core-0.9.6.dist-info/WHEEL
encoded_core-0.9.6.dist-info/entry_points.txt
encoded_core-0.9.6.dist-info/RECORD
